{
  "package-0/uncore|uJ": 1892,
  "psys|uJ": 120484,
  "package-0/dram|uJ": 7813,
  "package-0|uJ": 44678,
  "uncore|uJ": 1892,
  "duration|ns": 4359072,
  "dram|mW": 1792,
  "core|mW": 7463,
  "device|mW": 12041,
  "package|uJ": 44678,
  "package-0/dram|mW": 1792,
  "dram|uJ": 7813,
  "package-0/core|uJ": 32532,
  "package-0/core|mW": 7463,
  "device|uJ": 52491,
  "core|uJ": 32532,
  "package-0/uncore|mW": 434,
  "package-0|mW": 10249,
  "package|mW": 10249,
  "psys|mW": 27639,
  "uncore|mW": 434
}