{
  "package-0/uncore|uJ": 10803,
  "psys|uJ": 2391230,
  "package-0/dram|uJ": 126586,
  "package-0|uJ": 923948,
  "uncore|uJ": 10803,
  "duration|ns": 84302172,
  "dram|mW": 1501,
  "core|mW": 9199,
  "device|mW": 12461,
  "package|uJ": 923948,
  "package-0/dram|mW": 1501,
  "dram|uJ": 126586,
  "package-0/core|uJ": 775571,
  "package-0/core|mW": 9199,
  "device|uJ": 1050534,
  "core|uJ": 775571,
  "package-0/uncore|mW": 128,
  "package-0|mW": 10959,
  "package|mW": 10959,
  "psys|mW": 28364,
  "uncore|mW": 128
}