{
  "package-0/uncore|uJ": 61,
  "psys|uJ": 40648,
  "package-0/dram|uJ": 2319,
  "package-0|uJ": 33997,
  "uncore|uJ": 61,
  "duration|ns": 1960513,
  "dram|mW": 1182,
  "core|mW": 10148,
  "device|mW": 18523,
  "package|uJ": 33997,
  "package-0/dram|mW": 1182,
  "dram|uJ": 2319,
  "package-0/core|uJ": 19897,
  "package-0/core|mW": 10148,
  "device|uJ": 36316,
  "core|uJ": 19897,
  "package-0/uncore|mW": 31,
  "package-0|mW": 17340,
  "package|mW": 17340,
  "psys|mW": 20733,
  "uncore|mW": 31
}