{
  "package-0/uncore|uJ": 855,
  "psys|uJ": 29298,
  "package-0/dram|uJ": 3112,
  "package-0|uJ": 25329,
  "uncore|uJ": 855,
  "duration|ns": 2313861,
  "dram|mW": 1344,
  "core|mW": 8124,
  "device|mW": 12291,
  "package|uJ": 25329,
  "package-0/dram|mW": 1344,
  "dram|uJ": 3112,
  "package-0/core|uJ": 18799,
  "package-0/core|mW": 8124,
  "device|uJ": 28441,
  "core|uJ": 18799,
  "package-0/uncore|mW": 369,
  "package-0|mW": 10946,
  "package|mW": 10946,
  "psys|mW": 12661,
  "uncore|mW": 369
}