{
  "package-0/uncore|uJ": 1160,
  "psys|uJ": 130126,
  "package-0/dram|uJ": 8789,
  "package-0|uJ": 48828,
  "uncore|uJ": 1160,
  "duration|ns": 3715330,
  "dram|mW": 2365,
  "core|mW": 10628,
  "device|mW": 15507,
  "package|uJ": 48828,
  "package-0/dram|mW": 2365,
  "dram|uJ": 8789,
  "package-0/core|uJ": 39489,
  "package-0/core|mW": 10628,
  "device|uJ": 57617,
  "core|uJ": 39489,
  "package-0/uncore|mW": 312,
  "package-0|mW": 13142,
  "package|mW": 13142,
  "psys|mW": 35024,
  "uncore|mW": 312
}