{
  "package-0/uncore|uJ": 9460,
  "psys|uJ": 537840,
  "package-0/dram|uJ": 33874,
  "package-0|uJ": 200988,
  "uncore|uJ": 9460,
  "duration|ns": 14671541,
  "dram|mW": 2308,
  "core|mW": 10133,
  "device|mW": 16007,
  "package|uJ": 200988,
  "package-0/dram|mW": 2308,
  "dram|uJ": 33874,
  "package-0/core|uJ": 148681,
  "package-0/core|mW": 10133,
  "device|uJ": 234862,
  "core|uJ": 148681,
  "package-0/uncore|mW": 644,
  "package-0|mW": 13699,
  "package|mW": 13699,
  "psys|mW": 36658,
  "uncore|mW": 644
}