{
  "package-0/uncore|uJ": 10193,
  "psys|uJ": 2715202,
  "package-0/dram|uJ": 118530,
  "package-0|uJ": 1042173,
  "uncore|uJ": 10193,
  "duration|ns": 78954020,
  "dram|mW": 1501,
  "core|mW": 10261,
  "device|mW": 14700,
  "package|uJ": 1042173,
  "package-0/dram|mW": 1501,
  "dram|uJ": 118530,
  "package-0/core|uJ": 810179,
  "package-0/core|mW": 10261,
  "device|uJ": 1160703,
  "core|uJ": 810179,
  "package-0/uncore|mW": 129,
  "package-0|mW": 13199,
  "package|mW": 13199,
  "psys|mW": 34389,
  "uncore|mW": 129
}